pyramid_authsanity/__init__.py
pyramid_authsanity/interfaces.py
pyramid_authsanity/policy.py
pyramid_authsanity/sources.py
pyramid_authsanity/util.py
pyramid_authsanity-2.0.0.dist-info/LICENSE
pyramid_authsanity-2.0.0.dist-info/METADATA
pyramid_authsanity-2.0.0.dist-info/WHEEL
pyramid_authsanity-2.0.0.dist-info/top_level.txt
pyramid_authsanity-2.0.0.dist-info/RECORD
