Metadata-Version: 2.1
Name: pyramid-authsanity
Version: 2.0.0
Summary: An auth policy for the Pyramid Web Framework with sane defaults.
Home-page: https://github.com/usingnamespace/pyramid_authsanity
Author: Bert JW Regeer
Author-email: bertjw@regeer.org
License: UNKNOWN
Keywords: pyramid authorization policy
Platform: UNKNOWN
Classifier: Development Status :: 5 - Production/Stable
Classifier: Framework :: Pyramid
Classifier: Intended Audience :: Developers
Classifier: License :: OSI Approved :: ISC License (ISCL)
Classifier: Programming Language :: Python
Classifier: Programming Language :: Python :: 3.6
Classifier: Programming Language :: Python :: 3.7
Classifier: Programming Language :: Python :: 3.8
Classifier: Programming Language :: Python :: 3.9
Classifier: Programming Language :: Python :: Implementation :: CPython
Classifier: Programming Language :: Python :: Implementation :: PyPy
Requires-Python: >=3.6
Requires-Dist: pyramid (>=2.0)
Requires-Dist: zope.interface
Requires-Dist: pyramid-services (>=2.0)
Provides-Extra: docs
Requires-Dist: pyramid (>=2.0) ; extra == 'docs'
Requires-Dist: zope.interface ; extra == 'docs'
Requires-Dist: pyramid-services (>=2.0) ; extra == 'docs'
Requires-Dist: sphinx ; extra == 'docs'
Requires-Dist: repoze.sphinx.autointerface ; extra == 'docs'
Provides-Extra: testing
Requires-Dist: pyramid (>=2.0) ; extra == 'testing'
Requires-Dist: zope.interface ; extra == 'testing'
Requires-Dist: pyramid-services (>=2.0) ; extra == 'testing'
Requires-Dist: pytest ; extra == 'testing'
Requires-Dist: coverage ; extra == 'testing'
Requires-Dist: pytest-cov ; extra == 'testing'
